polytrend/__init__.py
polytrend/polytrend.py
polytrend-1.0.9.dist-info/LICENSE
polytrend-1.0.9.dist-info/METADATA
polytrend-1.0.9.dist-info/WHEEL
polytrend-1.0.9.dist-info/top_level.txt
polytrend-1.0.9.dist-info/RECORD
