Metadata-Version: 2.1
Name: polytrend
Version: 1.0.9
Summary: PolyTrend is a regression tool that fits polynomial curves to noisy data.
Author-email: Emmanuel Asiimwe <asiimwemmanuel47@gmail.com>
Project-URL: Homepage, https://github.com/asiimwemmanuel/polytrend
Project-URL: Issues, https://github.com/asiimwemmanuel/polytrend/issues
Classifier: Programming Language :: Python :: 3.11
Classifier: License :: OSI Approved :: GNU General Public License v3 or later (GPLv3+)
Classifier: Operating System :: OS Independent
Requires-Python: >=3.11.8
License-File: LICENSE
Requires-Dist: cx-Freeze ~=6.15.16
Requires-Dist: matplotlib ~=3.8.3
Requires-Dist: numpy ~=1.26.4
Requires-Dist: pandas ~=2.2.1
Requires-Dist: PyQt6 ~=6.6.1
Requires-Dist: PyQt6-sip ~=13.6.0
Requires-Dist: scikit-learn ~=1.4.1.post1
Requires-Dist: setuptools ~=65.5.0
